table_widget/__init__.py
table_widget/static/widget.css
table_widget/static/widget.js
table_widget-0.0.3.dist-info/METADATA
table_widget-0.0.3.dist-info/WHEEL
table_widget-0.0.3.dist-info/RECORD
