Metadata-Version: 2.4
Name: table_widget
Version: 0.0.3
Requires-Dist: anywidget
Requires-Dist: pandas
Provides-Extra: dev
Requires-Dist: jupyterlab; extra == 'dev'
Requires-Dist: watchfiles; extra == 'dev'
